x_tools/pylint/.pylintrc
x_tools/pylint/__init__.py
x_tools/pylint/msg_defs.py
x_tools/pylint/msg_wrns.py
x_tools/pylint/models/__init__.py
x_tools/pylint/models/mdl_msg_defs.py
x_tools/pylint/models/mdl_reports.py
x_tools/pylint/models/mdl_wrn_msg.py
x_tools/pylint/models/tp_msg_id.py
x_tools_pylint-0.2.1.dist-info/METADATA
x_tools_pylint-0.2.1.dist-info/WHEEL
x_tools_pylint-0.2.1.dist-info/top_level.txt
x_tools_pylint-0.2.1.dist-info/RECORD
