Metadata-Version: 2.4
Name: x_tools-pylint
Version: 0.2.1
Summary: PyLint - Pomocný nástroj pro správu kódu
Author-email: Milan Brzoň <milan.brzon@generaliceska.cz>
Classifier: Programming Language :: Python :: 3
Classifier: Operating System :: OS Independent
Requires-Python: >=3.9
Requires-Dist: x_tools-utils~=0.2.0
Requires-Dist: pydantic~=2.11.7
Requires-Dist: tabulate~=0.9.0
Requires-Dist: pylint~=3.3.8
